ModuBotCore/__init__.py
ModuBotCore/config/__init__.py
ModuBotCore/config/logger.py
ModuBotCore/helpers/__init__.py
ModuBotCore/modules/__init__.py
modubotcore-0.0.3.dist-info/licenses/LICENSE
modubotcore-0.0.3.dist-info/METADATA
modubotcore-0.0.3.dist-info/WHEEL
modubotcore-0.0.3.dist-info/top_level.txt
modubotcore-0.0.3.dist-info/RECORD
