Metadata-Version: 2.4
Name: ModuBotCore
Version: 0.0.3
Summary: Core utilities for ModuBot-based bots
Author-email: Endkind <endkind.ender@endkind.net>
Requires-Python: >=3.9
License-File: LICENSE
Requires-Dist: python-dotenv>=1.1.0
Dynamic: license-file
